multi_recommender/__init__.py
multi_recommender/__main__.py
multi_recommender/pipeline_registry.py
multi_recommender/settings.py
multi_recommender/pipelines/__init__.py
multi_recommender/pipelines/build_recommendations_based_similar/__init__.py
multi_recommender/pipelines/build_recommendations_based_similar/nodes.py
multi_recommender/pipelines/build_recommendations_based_similar/pipeline.py
multi_recommender/pipelines/build_recommendations_based_similar/scripts/__init__.py
multi_recommender/pipelines/build_recommendations_based_similar/scripts/anime_pipeline_module.py
tests/pipelines/__init__.py
tests/pipelines/build_recommendations_based_similar/__init__.py
tests/pipelines/build_recommendations_based_similar/test_pipeline.py
multi_recommender-0.1.dist-info/METADATA
multi_recommender-0.1.dist-info/WHEEL
multi_recommender-0.1.dist-info/entry_points.txt
multi_recommender-0.1.dist-info/top_level.txt
multi_recommender-0.1.dist-info/RECORD
